napalm_panos/__init__.py
napalm_panos/panos.py
napalm_panos/templates/.placeholder
napalm_panos/templates/set_hostname.j2
napalm_panos/utils/__init__.py
napalm_panos/utils/textfsm_templates/.placeholder
napalm_panos-0.7.0.dist-info/AUTHORS
napalm_panos-0.7.0.dist-info/LICENSE
napalm_panos-0.7.0.dist-info/METADATA
napalm_panos-0.7.0.dist-info/WHEEL
napalm_panos-0.7.0.dist-info/RECORD
