Metadata-Version: 2.3
Name: napalm_panos
Version: 0.7.0
Summary: Network Automation and Programmability Abstraction Layer with Multivendor support for PANOS.
License: Apache-2.0
Keywords: napalm,panos,napalm-panos
Author: Gabriele Gerbino
Author-email: gabriele@networktocode.com
Requires-Python: >=3.10,<3.14
Classifier: Development Status :: 4 - Beta
Classifier: Intended Audience :: Developers
Classifier: License :: OSI Approved :: Apache Software License
Classifier: Programming Language :: Python :: 3
Classifier: Programming Language :: Python :: 3.10
Classifier: Programming Language :: Python :: 3.11
Classifier: Programming Language :: Python :: 3.12
Classifier: Programming Language :: Python :: 3.13
Requires-Dist: cffi (>=1.17.1)
Requires-Dist: cryptography (>=42.0.0)
Requires-Dist: lxml (>=5.0.0,<6.0.0)
Requires-Dist: napalm (>=5.0.0,<6.0.0)
Requires-Dist: netmiko (>=4.4.0,<5.0.0)
Requires-Dist: pan-python
Requires-Dist: requests-toolbelt
Requires-Dist: xmltodict
Project-URL: Documentation, https://github.com/napalm-automation/napalm-panos
Project-URL: Homepage, https://github.com/napalm-automation/napalm-panos
Project-URL: Repository, https://github.com/napalm-automation/napalm-panos
